kix/__init__.py
kix/color.py
kix/dict_expander.py
kix/log.py
kix/logger.py
kix/prompt.py
kix/utils/__init__.py
kix/utils/pather.py
kix/utils/truncate.py
kix-0.1.6.dist-info/METADATA
kix-0.1.6.dist-info/WHEEL
kix-0.1.6.dist-info/top_level.txt
kix-0.1.6.dist-info/RECORD
