Metadata-Version: 2.1
Name: kix
Version: 0.1.6
Summary: Package Description.
Home-page: https://github.com/krinj
Author: Jakrin Juangbhanich
Author-email: juangbhanich.k@gmail.com
License: UNKNOWN
Platform: UNKNOWN
Classifier: Programming Language :: Python :: 3.7
